thereispythonlibraryforthis/__init__.py
thereispythonlibraryforthis/config.py
thereispythonlibraryforthis/core.py
thereispythonlibraryforthis/data.py
thereispythonlibraryforthis/sarcasm.py
thereispythonlibraryforthis/utils.py
thereispythonlibraryforthis/cli/__init__.py
thereispythonlibraryforthis/cli/main.py
thereispythonlibraryforthis/scripts/__init__.py
thereispythonlibraryforthis/scripts/build_cache.py
thereispythonlibraryforthis-0.1.0.dist-info/METADATA
thereispythonlibraryforthis-0.1.0.dist-info/WHEEL
thereispythonlibraryforthis-0.1.0.dist-info/entry_points.txt
thereispythonlibraryforthis-0.1.0.dist-info/top_level.txt
thereispythonlibraryforthis-0.1.0.dist-info/RECORD
