Metadata-Version: 2.4
Name: thereispythonlibraryforthis
Version: 0.1.0
Summary: Because there is literally a Python library for everything.
Author-email: Siddharth Patel <siddharth2000patel@gmail.com>
License-Expression: MIT
Requires-Python: >=3.8
Requires-Dist: requests
Requires-Dist: rapidfuzz
